{
  "chapter": "🧬 الأحياء — الصف العاشر — الفصل الثاني",
  "description": "12 سؤالاً",
  "questions": [
    {
      "type": "mcq",
      "q": "جميع الحيوانات على ّ",
      "opts": [
        "تحتوي على بالستيدات خضراء",
        "حقيقية الّنواة"
      ],
      "ans": 1,
      "exp": "الإجابة الصحيحة: حقيقية الّنواة"
    },
    {
      "type": "mcq",
      "q": "أحد الحيوانات لها تماثل ُثنائي الجانب :",
      "opts": [
        "الهيد ار",
        "جراد البحر"
      ],
      "ans": 1,
      "exp": "الإجابة الصحيحة: جراد البحر"
    },
    {
      "type": "mcq",
      "q": "أحد خصائص الإسفنجيات أنها:",
      "opts": [
        "تتحرك",
        "ال ّ"
      ],
      "ans": 1,
      "exp": "الإجابة الصحيحة: ال ّ"
    },
    {
      "type": "mcq",
      "q": "خالل مراحل ال ّتكاثر الجنسي لدى الالّسعات :",
      "opts": [
        "ّ",
        "المنطلقة في الماء انقساماً ميتوزيًّا  تُ ّ",
        "تنقسم األمشاج ُ"
      ],
      "ans": 0,
      "exp": "الإجابة الصحيحة: ّ"
    },
    {
      "type": "mcq",
      "q": "أحد الخصائص ليست من ّ",
      "opts": [
        "التماثل الشعاعي",
        "التكاثر",
        "التنفس"
      ],
      "ans": 1,
      "exp": "الإجابة الصحيحة: التكاثر"
    },
    {
      "type": "mcq",
      "q": "واحدة مما يلي ال ُتعتبر من خصائص الخاليا",
      "opts": [
        "تساعدها على المشي",
        "تكشف الضوء",
        "تكشف المو ّاد",
        "تكشف"
      ],
      "ans": 0,
      "exp": "الإجابة الصحيحة: تساعدها على المشي"
    },
    {
      "type": "mcq",
      "q": "الطور اليرقي ل ّ",
      "opts": [
        "شعاعي رباعي األجزاء",
        "غير",
        "ثنائي الجانب",
        "شعاعي خماسي األجزاء"
      ],
      "ans": 2,
      "exp": "الإجابة الصحيحة: ثنائي الجانب"
    },
    {
      "type": "mcq",
      "q": "تركيبات مزدوجة في منطقة البلعوم لدى بعض",
      "opts": [
        "ال ّذيل",
        "الترشيح",
        "االنتشار"
      ],
      "ans": 1,
      "exp": "الإجابة الصحيحة: الترشيح"
    },
    {
      "type": "mcq",
      "q": "أغلب الفقاريات تتميز بأن لها:",
      "opts": [
        "يبقى الحبل الظهري كما هو",
        "لا يحدث تغيير لتركيب الحبل الشوكي",
        "يحتوي هيكلها على ّ",
        "تنمو النهاية األمامية للحبل الشوكي وتتطور ّ"
      ],
      "ans": 3,
      "exp": "الإجابة الصحيحة: تنمو النهاية األمامية للحبل الشوكي وتتطور ّ"
    },
    {
      "type": "mcq",
      "q": "أحد خصائص الجهاز الدوري لدى األسماك :",
      "opts": [
        "ّ",
        "يحتوي على قلب غير حقيقي",
        "ُ يعتَبر من النوع المفتوح"
      ],
      "ans": 0,
      "exp": "الإجابة الصحيحة: ّ"
    },
    {
      "type": "mcq",
      "q": "جميع التكيفات التالية تساعد الطيور على الطيران ما عدا:",
      "opts": [
        "المناقير",
        "شكل األجنحة",
        "نوع ّ",
        "عضالت ّ"
      ],
      "ans": 0,
      "exp": "الإجابة الصحيحة: المناقير"
    },
    {
      "type": "mcq",
      "q": "أحد الخصائص ال ّتالية ليست من ُم ّ",
      "opts": [
        "أعضائها ال",
        "لديها أمعاء قصيرة ًّ",
        "ُ ي ً",
        "هضم األنسجة النباتية فيها تستغرق وقتًا"
      ],
      "ans": 1,
      "exp": "الإجابة الصحيحة: لديها أمعاء قصيرة ًّ"
    }
  ]
}