{
  "chapter": "☪️ التربية الإسلامية — الثاني عشر أدبي — الفصل الثاني",
  "description": "25 سؤالاً — الثاني عشر أدبي",
  "questions": [
    {
      "type": "mcq",
      "q": "الإيمان بالملائكة يعني:",
      "opts": [
        "إنكارهم",
        "التصديق بوجودهم",
        "عبادتهم",
        "تجاهلهم"
      ],
      "ans": 1,
      "exp": "التصديق بوجودهم."
    },
    {
      "type": "mcq",
      "q": "الإيمان بالكتب:",
      "opts": [
        "كتاب واحد",
        "جميع الكتب السماوية",
        "كتاب البشر",
        "لا شيء"
      ],
      "ans": 1,
      "exp": "الإجابة الصحيحة: جميع الكتب السماوية."
    },
    {
      "type": "mcq",
      "q": "الإيمان بالرسل:",
      "opts": [
        "نبي واحد",
        "جميع الأنبياء",
        "بعضهم",
        "لا أحد"
      ],
      "ans": 1,
      "exp": "الإجابة الصحيحة: جميع الأنبياء."
    },
    {
      "type": "mcq",
      "q": "اليوم الآخر يعني:",
      "opts": [
        "الدنيا",
        "الآخرة",
        "الحياة",
        "النوم"
      ],
      "ans": 1,
      "exp": "الآخرة."
    },
    {
      "type": "mcq",
      "q": "القضاء والقدر:",
      "opts": [
        "عشوائي",
        "من الله",
        "من الإنسان",
        "غير معروف"
      ],
      "ans": 1,
      "exp": "الإجابة الصحيحة: من الله."
    },
    {
      "type": "mcq",
      "q": "الإيمان بالقضاء والقدر يعني:",
      "opts": [
        "إنكار القدر",
        "الاعتقاد بأن كل شيء بقدر الله",
        "الاعتماد على النفس فقط",
        "العشوائية"
      ],
      "ans": 1,
      "exp": "الاعتقاد بأن كل شيء بقدر الله."
    },
    {
      "type": "mcq",
      "q": "من ثمرات الإيمان:",
      "opts": [
        "القلق",
        "الطمأنينة",
        "الخوف",
        "الحزن"
      ],
      "ans": 1,
      "exp": "من ذلك: الطمأنينة."
    },
    {
      "type": "mcq",
      "q": "التوكل على الله يعني:",
      "opts": [
        "ترك العمل",
        "الاعتماد على الله مع الأخذ بالأسباب",
        "الاعتماد على النفس فقط",
        "الكسل"
      ],
      "ans": 1,
      "exp": "الاعتماد على الله مع الأخذ بالأسباب."
    },
    {
      "type": "mcq",
      "q": "الشكر يكون بـ:",
      "opts": [
        "اللسان",
        "العمل",
        "القلب",
        "جميع ما سبق"
      ],
      "ans": 3,
      "exp": "الإجابة الصحيحة: جميع ما سبق."
    },
    {
      "type": "mcq",
      "q": "الصبر أنواع:",
      "opts": [
        "نوع واحد",
        "نوعان",
        "ثلاثة أنواع",
        "أربعة"
      ],
      "ans": 2,
      "exp": "الإجابة الصحيحة: ثلاثة أنواع."
    },
    {
      "type": "mcq",
      "q": "من أنواع الصبر:",
      "opts": [
        "على الطاعة",
        "عن المعصية",
        "على البلاء",
        "جميع ما سبق"
      ],
      "ans": 3,
      "exp": "من ذلك: جميع ما سبق."
    },
    {
      "type": "mcq",
      "q": "الإخلاص يعني:",
      "opts": [
        "الرياء",
        "العمل لله وحده",
        "العمل للناس",
        "العمل للمال"
      ],
      "ans": 1,
      "exp": "العمل لله وحده."
    },
    {
      "type": "mcq",
      "q": "الرياء هو:",
      "opts": [
        "العمل لله",
        "العمل للناس",
        "العمل للعلم",
        "العمل للخير"
      ],
      "ans": 1,
      "exp": "الإجابة الصحيحة: العمل للناس."
    },
    {
      "type": "mcq",
      "q": "الحلال هو:",
      "opts": [
        "الممنوع",
        "المباح",
        "المكروه",
        "المحرم"
      ],
      "ans": 1,
      "exp": "الإجابة الصحيحة: المباح."
    },
    {
      "type": "mcq",
      "q": "الحرام هو:",
      "opts": [
        "المباح",
        "الممنوع",
        "المستحب",
        "الجائز"
      ],
      "ans": 1,
      "exp": "الإجابة الصحيحة: الممنوع."
    },
    {
      "type": "mcq",
      "q": "الغيبة هي:",
      "opts": [
        "مدح الناس",
        "ذكر عيوبهم في غيابهم",
        "مساعدتهم",
        "نصحهم"
      ],
      "ans": 1,
      "exp": "الإجابة الصحيحة: ذكر عيوبهم في غيابهم."
    },
    {
      "type": "mcq",
      "q": "النميمة هي:",
      "opts": [
        "نقل الكلام للإصلاح",
        "نقل الكلام للإفساد",
        "السكوت",
        "النصيحة"
      ],
      "ans": 1,
      "exp": "الإجابة الصحيحة: نقل الكلام للإفساد."
    },
    {
      "type": "mcq",
      "q": "الأمانة تشمل:",
      "opts": [
        "المال",
        "القول",
        "العمل",
        "جميع ما سبق"
      ],
      "ans": 3,
      "exp": "الإجابة الصحيحة: جميع ما سبق."
    },
    {
      "type": "mcq",
      "q": "من صفات المسلم:",
      "opts": [
        "الصدق",
        "الأمانة",
        "الإخلاص",
        "جميع ما سبق"
      ],
      "ans": 3,
      "exp": "من ذلك: جميع ما سبق."
    },
    {
      "type": "mcq",
      "q": "بر الوالدين يكون بـ:",
      "opts": [
        "الطاعة",
        "الاحترام",
        "الإحسان",
        "جميع ما سبق"
      ],
      "ans": 3,
      "exp": "الإجابة الصحيحة: جميع ما سبق."
    },
    {
      "type": "mcq",
      "q": "صلة الرحم تعني:",
      "opts": [
        "قطع العلاقات",
        "التواصل مع الأقارب",
        "تجاهلهم",
        "الخصام"
      ],
      "ans": 1,
      "exp": "التواصل مع الأقارب."
    },
    {
      "type": "mcq",
      "q": "حسن الخلق يؤدي إلى:",
      "opts": [
        "الكراهية",
        "المحبة",
        "الحزن",
        "الخوف"
      ],
      "ans": 1,
      "exp": "الإجابة الصحيحة: المحبة."
    },
    {
      "type": "mcq",
      "q": "الغش:",
      "opts": [
        "جائز",
        "محرم",
        "مستحب",
        "مكروه"
      ],
      "ans": 1,
      "exp": "الإجابة الصحيحة: محرم."
    },
    {
      "type": "mcq",
      "q": "التعاون يكون على:",
      "opts": [
        "الشر",
        "الخير",
        "الفوضى",
        "الكسل"
      ],
      "ans": 1,
      "exp": "الإجابة الصحيحة: الخير."
    },
    {
      "type": "mcq",
      "q": "الإسلام يدعو إلى:",
      "opts": [
        "العنف",
        "السلام",
        "الظلم",
        "الفوضى"
      ],
      "ans": 1,
      "exp": "الإجابة الصحيحة: السلام."
    }
  ]
}