{
  "chapter": "🔢 الرياضيات — الحادي عشر علمي — الفصل الأول",
  "description": "20 سؤالاً — الحادي عشر علمي",
  "questions": [
    {
      "type": "mcq",
      "q": "مجموعة الأعداد الحقيقية (R) تشمل:",
      "opts": [
        "الأعداد الطبيعية فقط",
        "الأعداد الصحيحة فقط",
        "جميع الأعداد (النسبية وغير النسبية)",
        "الأعداد السالبة فقط"
      ],
      "ans": 2,
      "exp": "الإجابة الصحيحة: جميع الأعداد (النسبية وغير النسبية). (ضمن موضوع: 🔵 الفصل: الفصل الأول)"
    },
    {
      "type": "mcq",
      "q": "العدد √2 يعتبر:",
      "opts": [
        "عدد نسبي",
        "عدد صحيح",
        "عدد غير نسبي",
        "عدد طبيعي"
      ],
      "ans": 2,
      "exp": "الإجابة الصحيحة: عدد غير نسبي. (ضمن موضوع: 🔵 الفصل: الفصل الأول)"
    },
    {
      "type": "mcq",
      "q": "القيمة المطلقة للعدد -5 هي:",
      "opts": [
        "-5",
        "5",
        "0",
        "10"
      ],
      "ans": 1,
      "exp": "القيمة الصحيحة: 5."
    },
    {
      "type": "mcq",
      "q": "|x| = 3 تعني:",
      "opts": [
        "x = 3 فقط",
        "x = -3 فقط",
        "x = 3 أو -3",
        "x = 0"
      ],
      "ans": 2,
      "exp": "x = 3 أو -3. (من موضوع: 🔵 الفصل: الفصل الأول)"
    },
    {
      "type": "mcq",
      "q": "حل المتباينة x > 2 يكون:",
      "opts": [
        "x < 2",
        "x = 2",
        "x > 2",
        "x ≤ 2"
      ],
      "ans": 2,
      "exp": "الإجابة الصحيحة: x > 2. (ضمن موضوع: 🔵 الفصل: الفصل الأول)"
    },
    {
      "type": "mcq",
      "q": "الفترة (2,5) تعني:",
      "opts": [
        "تشمل 2 و 5",
        "لا تشمل 2 و 5",
        "تشمل 2 فقط",
        "تشمل 5 فقط"
      ],
      "ans": 1,
      "exp": "لا تشمل 2 و 5. (من موضوع: 🔵 الفصل: الفصل الأول)"
    },
    {
      "type": "mcq",
      "q": "الفترة [2,5] تعني:",
      "opts": [
        "لا تشمل الطرفين",
        "تشمل 2 فقط",
        "تشمل 5 فقط",
        "تشمل 2 و 5"
      ],
      "ans": 3,
      "exp": "تشمل 2 و 5. (من موضوع: 🔵 الفصل: الفصل الأول)"
    },
    {
      "type": "mcq",
      "q": "حل المعادلة x + 3 = 7 هو:",
      "opts": [
        "3",
        "4",
        "5",
        "6"
      ],
      "ans": 1,
      "exp": "القيمة الصحيحة: 4."
    },
    {
      "type": "mcq",
      "q": "حل المعادلة 2x = 10 هو:",
      "opts": [
        "2",
        "3",
        "5",
        "10"
      ],
      "ans": 2,
      "exp": "القيمة الصحيحة: 5."
    },
    {
      "type": "mcq",
      "q": "المعادلة التربيعية تكون من الدرجة:",
      "opts": [
        "الأولى",
        "الثانية",
        "الثالثة",
        "الرابعة"
      ],
      "ans": 1,
      "exp": "الإجابة الصحيحة: الثانية. (ضمن موضوع: 🔵 الفصل: الفصل الأول)"
    },
    {
      "type": "mcq",
      "q": "مثال على معادلة تربيعية:",
      "opts": [
        "x + 2 = 0",
        "x² + 3x + 2 = 0",
        "x³ + 1 = 0",
        "x = 5"
      ],
      "ans": 1,
      "exp": "الإجابة الصحيحة: x² + 3x + 2 = 0. (ضمن موضوع: 🔵 الفصل: الفصل الأول)"
    },
    {
      "type": "mcq",
      "q": "حل المعادلة x² = 9 هو:",
      "opts": [
        "3 فقط",
        "-3 فقط",
        "3 و -3",
        "0"
      ],
      "ans": 2,
      "exp": "القيمة الصحيحة: 3 و -3."
    },
    {
      "type": "mcq",
      "q": "إذا كانت |x - 2| = 4 فإن:",
      "opts": [
        "x = 6 أو -2",
        "x = 4 فقط",
        "x = 2 فقط",
        "x = -4 فقط"
      ],
      "ans": 0,
      "exp": "النتيجة: x = 6 أو -2."
    },
    {
      "type": "mcq",
      "q": "حل المتباينة |x| < 3 يكون:",
      "opts": [
        "x > 3",
        "-3 < x < 3",
        "x = 3",
        "x < -3"
      ],
      "ans": 1,
      "exp": "القيمة الصحيحة: -3 < x < 3."
    },
    {
      "type": "mcq",
      "q": "إذا كان x² ≥ 0 فإن:",
      "opts": [
        "دائمًا موجب",
        "دائمًا سالب",
        "دائمًا ≥ 0",
        "غير معرف"
      ],
      "ans": 2,
      "exp": "النتيجة: دائمًا ≥ 0."
    },
    {
      "type": "mcq",
      "q": "الجذر التربيعي لـ 16 هو:",
      "opts": [
        "2",
        "4",
        "8",
        "16"
      ],
      "ans": 1,
      "exp": "القيمة الصحيحة: 4."
    },
    {
      "type": "mcq",
      "q": "حل المعادلة x² - 4 = 0 هو:",
      "opts": [
        "2 فقط",
        "-2 فقط",
        "2 و -2",
        "0"
      ],
      "ans": 2,
      "exp": "القيمة الصحيحة: 2 و -2."
    },
    {
      "type": "mcq",
      "q": "إذا كان x > 0 فإن |x| =",
      "opts": [
        "-x",
        "x",
        "0",
        "غير معرف"
      ],
      "ans": 1,
      "exp": "النتيجة: x."
    },
    {
      "type": "mcq",
      "q": "إذا كان x < 0 فإن |x| =",
      "opts": [
        "x",
        "-x",
        "0",
        "1"
      ],
      "ans": 1,
      "exp": "النتيجة: -x."
    },
    {
      "type": "mcq",
      "q": "المتباينات تستخدم لتمثيل:",
      "opts": [
        "قيمة واحدة",
        "مجموعة حلول",
        "عدد ثابت",
        "معادلة فقط"
      ],
      "ans": 1,
      "exp": "الإجابة الصحيحة: مجموعة حلول. (ضمن موضوع: 🔵 الفصل: الفصل الأول)"
    }
  ]
}