{
  "chapter": "📊 الإحصاء — الثاني عشر أدبي — الفصل الأول",
  "description": "20 سؤالاً — الثاني عشر أدبي",
  "questions": [
    {
      "type": "mcq",
      "q": "ما هو المتوسط الحسابي؟",
      "opts": [
        "أكبر قيمة",
        "مجموع القيم ÷ عددها",
        "أصغر قيمة",
        "الفرق"
      ],
      "ans": 1,
      "exp": "مجموع القيم ÷ عددها."
    },
    {
      "type": "mcq",
      "q": "الوسيط هو:",
      "opts": [
        "أكبر قيمة",
        "القيمة الوسطى",
        "أصغر قيمة",
        "المجموع (نكمل إلى 20…)"
      ],
      "ans": 1,
      "exp": "الإجابة الصحيحة: القيمة الوسطى."
    },
    {
      "type": "mcq",
      "q": "المنوال هو:",
      "opts": [
        "أكبر قيمة",
        "أكثر القيم تكرارًا",
        "أصغر قيمة",
        "المتوسط"
      ],
      "ans": 1,
      "exp": "الإجابة الصحيحة: أكثر القيم تكرارًا."
    },
    {
      "type": "mcq",
      "q": "المجتمع الإحصائي هو:",
      "opts": [
        "عينة صغيرة",
        "جميع العناصر",
        "بيانات فقط",
        "جدول"
      ],
      "ans": 1,
      "exp": "الإجابة الصحيحة: جميع العناصر."
    },
    {
      "type": "mcq",
      "q": "العينة هي:",
      "opts": [
        "كل المجتمع",
        "جزء من المجتمع",
        "البيانات كلها",
        "جدول"
      ],
      "ans": 1,
      "exp": "الإجابة الصحيحة: جزء من المجتمع."
    },
    {
      "type": "mcq",
      "q": "البيانات الكمية هي:",
      "opts": [
        "وصفية",
        "رقمية",
        "نصية",
        "رمزية"
      ],
      "ans": 1,
      "exp": "الإجابة الصحيحة: رقمية."
    },
    {
      "type": "mcq",
      "q": "البيانات النوعية هي:",
      "opts": [
        "رقمية",
        "وصفية",
        "عددية",
        "حسابية"
      ],
      "ans": 1,
      "exp": "الإجابة الصحيحة: وصفية."
    },
    {
      "type": "mcq",
      "q": "الجدول التكراري يستخدم لـ:",
      "opts": [
        "الرسم",
        "تنظيم البيانات",
        "الحذف",
        "التبسيط"
      ],
      "ans": 1,
      "exp": "الإجابة الصحيحة: تنظيم البيانات."
    },
    {
      "type": "mcq",
      "q": "التكرار هو:",
      "opts": [
        "عدد القيم",
        "عدد مرات ظهور القيمة",
        "الفرق",
        "المتوسط"
      ],
      "ans": 1,
      "exp": "الإجابة الصحيحة: عدد مرات ظهور القيمة."
    },
    {
      "type": "mcq",
      "q": "الفئة في الجدول هي:",
      "opts": [
        "رقم",
        "مجموعة قيم",
        "قيمة واحدة",
        "متوسط"
      ],
      "ans": 1,
      "exp": "الإجابة الصحيحة: مجموعة قيم."
    },
    {
      "type": "mcq",
      "q": "المدى يساوي:",
      "opts": [
        "المتوسط",
        "أكبر قيمة - أصغر قيمة",
        "المجموع",
        "الفرق"
      ],
      "ans": 1,
      "exp": "الإجابة الصحيحة: أكبر قيمة - أصغر قيمة."
    },
    {
      "type": "mcq",
      "q": "البيانات غير المبوبة:",
      "opts": [
        "منظمة",
        "غير منظمة",
        "جدول",
        "رسم"
      ],
      "ans": 1,
      "exp": "الإجابة الصحيحة: غير منظمة."
    },
    {
      "type": "mcq",
      "q": "الرسم البياني يستخدم لـ:",
      "opts": [
        "الحذف",
        "التوضيح",
        "الجمع",
        "القسمة"
      ],
      "ans": 1,
      "exp": "الإجابة الصحيحة: التوضيح."
    },
    {
      "type": "mcq",
      "q": "الأعمدة البيانية تمثل:",
      "opts": [
        "نصوص",
        "بيانات",
        "جداول",
        "صور"
      ],
      "ans": 1,
      "exp": "الإجابة الصحيحة: بيانات."
    },
    {
      "type": "mcq",
      "q": "المدرج التكراري يستخدم لـ:",
      "opts": [
        "البيانات النوعية",
        "البيانات الكمية",
        "النصوص",
        "الصور"
      ],
      "ans": 1,
      "exp": "الإجابة الصحيحة: البيانات الكمية."
    },
    {
      "type": "mcq",
      "q": "المتوسط الحسابي يتأثر بـ:",
      "opts": [
        "القيم المتطرفة",
        "التكرار",
        "الوسيط",
        "المنوال"
      ],
      "ans": 0,
      "exp": "الإجابة الصحيحة: القيم المتطرفة."
    },
    {
      "type": "mcq",
      "q": "الوسيط لا يتأثر بـ:",
      "opts": [
        "القيم المتطرفة",
        "الترتيب",
        "البيانات",
        "القيم"
      ],
      "ans": 0,
      "exp": "الإجابة الصحيحة: القيم المتطرفة."
    },
    {
      "type": "mcq",
      "q": "المنوال يمثل:",
      "opts": [
        "أقل قيمة",
        "أكثر تكرار",
        "المتوسط",
        "الفرق"
      ],
      "ans": 1,
      "exp": "الإجابة الصحيحة: أكثر تكرار."
    },
    {
      "type": "mcq",
      "q": "الهدف من الإحصاء:",
      "opts": [
        "الترفيه",
        "تحليل البيانات",
        "اللعب",
        "الرسم فقط"
      ],
      "ans": 1,
      "exp": "الإجابة الصحيحة: تحليل البيانات."
    },
    {
      "type": "mcq",
      "q": "الإحصاء يستخدم في:",
      "opts": [
        "الاقتصاد",
        "الطب",
        "التعليم",
        "جميع ما سبق"
      ],
      "ans": 3,
      "exp": "الإجابة الصحيحة: جميع ما سبق."
    }
  ]
}